akkaserverless/__init__.py
akkaserverless/action_context.py
akkaserverless/action_protocol_entity.py
akkaserverless/action_servicer.py
akkaserverless/akkaserverless_service.py
akkaserverless/contexts.py
akkaserverless/discovery_servicer.py
akkaserverless/event_sourced_context.py
akkaserverless/event_sourced_entity.py
akkaserverless/eventsourced_servicer.py
akkaserverless/exceptions.py
akkaserverless/replicated_context.py
akkaserverless/replicated_entity.py
akkaserverless/replicated_servicer.py
akkaserverless/value_context.py
akkaserverless/value_entity.py
akkaserverless/value_servicer.py
akkaserverless/version.py
akkaserverless/view.py
akkaserverless/akkaserverless/annotations_pb2.py
akkaserverless/akkaserverless/annotations_pb2_grpc.py
akkaserverless/akkaserverless/component_pb2.py
akkaserverless/akkaserverless/component_pb2_grpc.py
akkaserverless/akkaserverless/eventing_pb2.py
akkaserverless/akkaserverless/eventing_pb2_grpc.py
akkaserverless/akkaserverless/legacy_entity_key_pb2.py
akkaserverless/akkaserverless/legacy_entity_key_pb2_grpc.py
akkaserverless/akkaserverless/views_pb2.py
akkaserverless/akkaserverless/views_pb2_grpc.py
akkaserverless/akkaserverless/component/component_pb2.py
akkaserverless/akkaserverless/component/component_pb2_grpc.py
akkaserverless/akkaserverless/component/action/action_pb2.py
akkaserverless/akkaserverless/component/action/action_pb2_grpc.py
akkaserverless/akkaserverless/component/entity/entity_pb2.py
akkaserverless/akkaserverless/component/entity/entity_pb2_grpc.py
akkaserverless/akkaserverless/component/eventsourcedentity/event_sourced_entity_pb2.py
akkaserverless/akkaserverless/component/eventsourcedentity/event_sourced_entity_pb2_grpc.py
akkaserverless/akkaserverless/component/replicatedentity/replicated_entity_pb2.py
akkaserverless/akkaserverless/component/replicatedentity/replicated_entity_pb2_grpc.py
akkaserverless/akkaserverless/component/valueentity/value_entity_pb2.py
akkaserverless-0.1.13.dist-info/LICENSE
akkaserverless-0.1.13.dist-info/METADATA
akkaserverless-0.1.13.dist-info/WHEEL
akkaserverless-0.1.13.dist-info/top_level.txt
akkaserverless-0.1.13.dist-info/RECORD
